silica-lab/examples/verilog_ex/top.v
// Simple 1-bit counter module
module top(
    input clk,
    input rst,
    output reg q
);
    always @(posedge clk or posedge rst) begin
        if (rst)
            q <= 1'b0;
        else
            q <= ~q;
    end
endmodule

silica-lab/examples/systemverilog_ex/tb.sv
`timescale 1ns/1ps

module tb;
    logic clk;
    logic rst;
    wire q;

    // Instantiate top
    top uut (
        .clk(clk),
        .rst(rst),
        .q(q)
    );

    // Clock generation
    initial clk = 0;
    always #5 clk = ~clk;

    // Test sequence
    initial begin
        $dumpfile("build/wave.vcd");
        $dumpvars(0, tb);

        rst = 1;
        #10;
        rst = 0;

        #100;
        $finish;
    end
endmodule

silica-lab-frontend/src-tauri/build/wave.vcd
$date
	Sat Nov 22 21:40:23 2025
$end
$version
	Icarus Verilog
$end
$timescale
	1ps
$end
$scope module tb $end
$var wire 1 ! q $end
$var reg 1 " clk $end
$var reg 1 # rst $end
$scope module uut $end
$var wire 1 " clk $end
$var wire 1 # rst $end
$var reg 1 ! q $end
$upscope $end
$upscope $end
$enddefinitions $end
$comment Show the parameter values. $end
$dumpall
$end
#0
$dumpvars
1#
0"
0!
$end
#5000
1"
#10000
0"
0#
#15000
1!
1"
#20000
0"
#25000
0!
1"
#30000
0"
#35000
1!
1"
#40000
0"
#45000
0!
1"
#50000
0"
#55000
1!
1"
#60000
0"
#65000
0!
1"
#70000
0"
#75000
1!
1"
#80000
0"
#85000
0!
1"
#90000
0"
#95000
1!
1"
#100000
0"
#105000
0!
1"
